hereutil/__init__.py
hereutil-0.1.5.dist-info/METADATA
hereutil-0.1.5.dist-info/WHEEL
hereutil-0.1.5.dist-info/RECORD
